{
	"content_type": "CG_SHOP_2025_Solution",
	"instance_uid": "simple-polygon-exterior_150_89d077ac_extract",
	"steiner_points_x": [
		"265/89",
		"879/37",
		56,
		36,
		75,
		124,
		118,
		133,
		"49761/362",
		93,
		"41527/445",
		"8333/89",
		117,
		91,
		89,
		"3592/33",
		94,
		67,
		63,
		42,
		53,
		73,
		70,
		36,
		15,
		34,
		26,
		"7299/997",
		40,
		90,
		32,
		19,
		77,
		"45816/593",
		58,
		100,
		146,
		141,
		132,
		173,
		175,
		143,
		"12566/73",
		"528/5",
		"12168/125",
		133,
		144,
		"85272/481",
		"14157/73",
		149,
		180,
		"131652/745",
		111
	],
	"steiner_points_y": [
		"12083/89",
		"4975/37",
		176,
		165,
		159,
		170,
		178,
		148,
		"53661/362",
		168,
		"76251/445",
		"14364/89",
		140,
		145,
		123,
		"3791/33",
		118,
		128,
		122,
		111,
		"3340/27",
		69,
		56,
		54,
		41,
		75,
		24,
		"43544/997",
		55,
		85,
		69,
		4,
		33,
		"13121/593",
		15,
		20,
		14,
		20,
		44,
		50,
		26,
		53,
		"3818/73",
		"376/5",
		"9424/125",
		114,
		91,
		"45033/481",
		"5975/73",
		176,
		137,
		"100739/745",
		190
	],
	"edges": [
		[
			132,
			206
		],
		[
			125,
			206
		],
		[
			125,
			132
		],
		[
			18,
			169
		],
		[
			19,
			169
		],
		[
			141,
			208
		],
		[
			142,
			208
		],
		[
			73,
			193
		],
		[
			192,
			193
		],
		[
			73,
			192
		],
		[
			77,
			196
		],
		[
			78,
			196
		],
		[
			37,
			98
		],
		[
			37,
			100
		],
		[
			98,
			100
		],
		[
			43,
			181
		],
		[
			44,
			181
		],
		[
			123,
			138
		],
		[
			123,
			161
		],
		[
			138,
			161
		],
		[
			70,
			191
		],
		[
			71,
			191
		],
		[
			133,
			135
		],
		[
			8,
			165
		],
		[
			165,
			167
		],
		[
			56,
			184
		],
		[
			178,
			184
		],
		[
			56,
			178
		],
		[
			107,
			202
		],
		[
			108,
			202
		],
		[
			135,
			205
		],
		[
			136,
			205
		],
		[
			194,
			197
		],
		[
			85,
			197
		],
		[
			85,
			194
		],
		[
			101,
			168
		],
		[
			20,
			101
		],
		[
			20,
			168
		],
		[
			123,
			163
		],
		[
			10,
			163
		],
		[
			10,
			123
		],
		[
			206,
			207
		],
		[
			126,
			206
		],
		[
			76,
			193
		],
		[
			76,
			192
		],
		[
			94,
			177
		],
		[
			93,
			177
		],
		[
			181,
			186
		],
		[
			44,
			186
		],
		[
			35,
			176
		],
		[
			36,
			176
		],
		[
			1,
			156
		],
		[
			120,
			201
		],
		[
			103,
			201
		],
		[
			103,
			120
		],
		[
			72,
			91
		],
		[
			91,
			194
		],
		[
			72,
			194
		],
		[
			110,
			204
		],
		[
			111,
			204
		],
		[
			127,
			130
		],
		[
			128,
			130
		],
		[
			27,
			173
		],
		[
			173,
			174
		],
		[
			27,
			174
		],
		[
			49,
			182
		],
		[
			50,
			182
		],
		[
			22,
			172
		],
		[
			170,
			172
		],
		[
			22,
			170
		],
		[
			38,
			98
		],
		[
			110,
			113
		],
		[
			120,
			168
		],
		[
			101,
			120
		],
		[
			11,
			163
		],
		[
			121,
			163
		],
		[
			11,
			121
		],
		[
			55,
			184
		],
		[
			102,
			120
		],
		[
			25,
			37
		],
		[
			37,
			173
		],
		[
			25,
			173
		],
		[
			45,
			180
		],
		[
			180,
			183
		],
		[
			45,
			183
		],
		[
			61,
			190
		],
		[
			62,
			190
		],
		[
			182,
			187
		],
		[
			53,
			182
		],
		[
			53,
			187
		],
		[
			46,
			183
		],
		[
			121,
			168
		],
		[
			10,
			161
		],
		[
			117,
			201
		],
		[
			119,
			201
		],
		[
			117,
			119
		],
		[
			137,
			205
		],
		[
			138,
			205
		],
		[
			177,
			185
		],
		[
			94,
			185
		],
		[
			15,
			169
		],
		[
			17,
			169
		],
		[
			15,
			17
		],
		[
			79,
			196
		],
		[
			23,
			170
		],
		[
			24,
			170
		],
		[
			41,
			179
		],
		[
			179,
			186
		],
		[
			41,
			186
		],
		[
			151,
			159
		],
		[
			152,
			159
		],
		[
			124,
			135
		],
		[
			125,
			135
		],
		[
			28,
			175
		],
		[
			29,
			175
		],
		[
			3,
			153
		],
		[
			4,
			153
		],
		[
			5,
			158
		],
		[
			4,
			158
		],
		[
			20,
			171
		],
		[
			7,
			160
		],
		[
			8,
			160
		],
		[
			38,
			185
		],
		[
			38,
			177
		],
		[
			127,
			206
		],
		[
			50,
			187
		],
		[
			51,
			187
		],
		[
			195,
			196
		],
		[
			80,
			195
		],
		[
			80,
			196
		],
		[
			122,
			163
		],
		[
			163,
			164
		],
		[
			105,
			202
		],
		[
			106,
			202
		],
		[
			97,
			185
		],
		[
			98,
			185
		],
		[
			84,
			193
		],
		[
			76,
			84
		],
		[
			109,
			114
		],
		[
			109,
			115
		],
		[
			57,
			178
		],
		[
			141,
			162
		],
		[
			146,
			162
		],
		[
			141,
			146
		],
		[
			60,
			188
		],
		[
			68,
			188
		],
		[
			60,
			68
		],
		[
			4,
			159
		],
		[
			158,
			159
		],
		[
			63,
			190
		],
		[
			64,
			190
		],
		[
			193,
			194
		],
		[
			72,
			193
		],
		[
			154,
			157
		],
		[
			155,
			157
		],
		[
			85,
			193
		],
		[
			9,
			165
		],
		[
			153,
			159
		],
		[
			69,
			191
		],
		[
			161,
			162
		],
		[
			9,
			161
		],
		[
			9,
			162
		],
		[
			104,
			202
		],
		[
			69,
			91
		],
		[
			69,
			92
		],
		[
			86,
			88
		],
		[
			86,
			197
		],
		[
			88,
			197
		],
		[
			60,
			190
		],
		[
			74,
			192
		],
		[
			131,
			206
		],
		[
			2,
			154
		],
		[
			90,
			194
		],
		[
			108,
			116
		],
		[
			109,
			116
		],
		[
			77,
			82
		],
		[
			77,
			83
		],
		[
			75,
			192
		],
		[
			124,
			205
		],
		[
			124,
			138
		],
		[
			64,
			66
		],
		[
			171,
			172
		],
		[
			21,
			172
		],
		[
			21,
			171
		],
		[
			77,
			195
		],
		[
			140,
			162
		],
		[
			39,
			177
		],
		[
			148,
			165
		],
		[
			149,
			165
		],
		[
			89,
			197
		],
		[
			109,
			203
		],
		[
			110,
			203
		],
		[
			54,
			182
		],
		[
			40,
			178
		],
		[
			40,
			184
		],
		[
			125,
			133
		],
		[
			33,
			175
		],
		[
			29,
			33
		],
		[
			25,
			170
		],
		[
			37,
			170
		],
		[
			67,
			190
		],
		[
			64,
			67
		],
		[
			76,
			83
		],
		[
			36,
			174
		],
		[
			37,
			174
		],
		[
			68,
			92
		],
		[
			41,
			184
		],
		[
			147,
			162
		],
		[
			52,
			187
		],
		[
			116,
			202
		],
		[
			139,
			162
		],
		[
			11,
			168
		],
		[
			143,
			145
		],
		[
			8,
			149
		],
		[
			13,
			15
		],
		[
			13,
			169
		],
		[
			3,
			154
		],
		[
			143,
			208
		],
		[
			145,
			208
		],
		[
			179,
			180
		],
		[
			54,
			179
		],
		[
			54,
			180
		],
		[
			127,
			131
		],
		[
			72,
			191
		],
		[
			54,
			184
		],
		[
			12,
			168
		],
		[
			40,
			177
		],
		[
			139,
			161
		],
		[
			45,
			179
		],
		[
			45,
			186
		],
		[
			6,
			160
		],
		[
			180,
			182
		],
		[
			195,
			198
		],
		[
			82,
			195
		],
		[
			60,
			67
		],
		[
			60,
			189
		],
		[
			12,
			20
		],
		[
			5,
			150
		],
		[
			26,
			173
		],
		[
			42,
			181
		],
		[
			146,
			208
		],
		[
			179,
			184
		],
		[
			175,
			176
		],
		[
			57,
			188
		],
		[
			57,
			92
		],
		[
			92,
			188
		],
		[
			58,
			188
		],
		[
			59,
			188
		],
		[
			149,
			160
		],
		[
			150,
			160
		],
		[
			177,
			178
		],
		[
			12,
			169
		],
		[
			89,
			194
		],
		[
			30,
			33
		],
		[
			1,
			155
		],
		[
			100,
			172
		],
		[
			30,
			32
		],
		[
			37,
			172
		],
		[
			81,
			195
		],
		[
			95,
			199
		],
		[
			34,
			175
		],
		[
			12,
			19
		],
		[
			41,
			181
		],
		[
			48,
			180
		],
		[
			48,
			182
		],
		[
			95,
			97
		],
		[
			5,
			160
		],
		[
			91,
			191
		],
		[
			9,
			147
		],
		[
			117,
			202
		],
		[
			97,
			200
		],
		[
			93,
			178
		],
		[
			57,
			93
		],
		[
			147,
			165
		],
		[
			104,
			117
		],
		[
			104,
			201
		],
		[
			35,
			175
		],
		[
			165,
			166
		],
		[
			94,
			97
		],
		[
			174,
			176
		]
	],
	"score": 0.5092592592592593
}