{
	"content_type": "CG_SHOP_2025_Solution",
	"instance_uid": "simple-polygon-exterior_250_a97729dd_extract_0",
	"steiner_points_x": [
		"-424345/4357",
		"-424142/4357",
		"-6571/67",
		-70,
		"-587/6",
		"-690/7",
		-97,
		"-1656/17",
		"-426985/4357",
		"-428956/4357",
		"-430611/4357",
		-47,
		-97,
		"-425863/4357",
		-74,
		-50,
		-65,
		-55,
		-55
	],
	"steiner_points_y": [
		"39239/4357",
		"52637/4357",
		"-2407/67",
		-15,
		-20,
		"-481/7",
		-31,
		"133/17",
		"-135001/4357",
		"-265087/4357",
		"-374317/4357",
		-6,
		-14,
		"-60949/4357",
		-3,
		5,
		-5,
		-10,
		-2
	],
	"edges": [
		[
			21,
			23
		],
		[
			21,
			24
		],
		[
			4,
			41
		],
		[
			4,
			48
		],
		[
			45,
			47
		],
		[
			41,
			45
		],
		[
			9,
			11
		],
		[
			43,
			45
		],
		[
			42,
			53
		],
		[
			53,
			55
		],
		[
			42,
			55
		],
		[
			8,
			42
		],
		[
			12,
			42
		],
		[
			8,
			12
		],
		[
			7,
			51
		],
		[
			6,
			51
		],
		[
			30,
			56
		],
		[
			55,
			56
		],
		[
			30,
			55
		],
		[
			5,
			45
		],
		[
			4,
			45
		],
		[
			34,
			53
		],
		[
			7,
			53
		],
		[
			7,
			34
		],
		[
			36,
			39
		],
		[
			36,
			46
		],
		[
			8,
			11
		],
		[
			8,
			53
		],
		[
			1,
			44
		],
		[
			1,
			49
		],
		[
			13,
			42
		],
		[
			25,
			29
		],
		[
			26,
			29
		],
		[
			31,
			55
		],
		[
			31,
			53
		],
		[
			24,
			54
		],
		[
			25,
			54
		],
		[
			5,
			43
		],
		[
			34,
			51
		],
		[
			35,
			51
		],
		[
			51,
			52
		],
		[
			43,
			51
		],
		[
			17,
			50
		],
		[
			18,
			50
		],
		[
			46,
			51
		],
		[
			18,
			20
		],
		[
			31,
			33
		],
		[
			33,
			53
		],
		[
			50,
			56
		],
		[
			56,
			57
		],
		[
			50,
			57
		],
		[
			14,
			42
		],
		[
			14,
			55
		],
		[
			14,
			56
		],
		[
			15,
			56
		],
		[
			54,
			57
		],
		[
			29,
			57
		],
		[
			29,
			54
		],
		[
			37,
			40
		],
		[
			20,
			50
		],
		[
			21,
			50
		],
		[
			36,
			40
		],
		[
			15,
			17
		],
		[
			21,
			54
		],
		[
			21,
			57
		],
		[
			6,
			43
		],
		[
			26,
			28
		],
		[
			30,
			57
		],
		[
			17,
			56
		],
		[
			2,
			48
		],
		[
			2,
			44
		],
		[
			3,
			48
		],
		[
			35,
			46
		]
	],
	"score": 0.32805
}