{
	"content_type": "CG_SHOP_2025_Solution",
	"instance_uid": "point-set_20_34a047f7",
	"steiner_points_x": [
		5852,
		"20835/4",
		6515,
		"852525/97",
		5889,
		6170,
		6265,
		"7314132/1597",
		"5075273/1229",
		7594,
		6540,
		"61591408/7985",
		6292,
		4207,
		8370,
		7570,
		7425,
		7497,
		7237,
		"46629084/7985",
		7810,
		"1780547/205",
		"68275/9",
		4385,
		6073,
		4286,
		"13086405/1597",
		"9647890/1597",
		"57555792/7985",
		"9981373/1597",
		5947,
		"6825255/1597",
		"943675/221",
		"61439858085/10157701",
		4180,
		7524,
		"5128575/1229",
		7851,
		6539
	],
	"steiner_points_y": [
		3316,
		"4013/2",
		"5302/3",
		"254025/97",
		3093,
		3174,
		3325,
		"5335404/1597",
		"3956860/1229",
		3058,
		2304,
		"28926076/7985",
		3114,
		3224,
		3190,
		1975,
		3049,
		3193,
		3272,
		"27581148/7985",
		3268,
		"670646/205",
		"32500/9",
		2365,
		1986,
		2411,
		"5854260/1597",
		"5545180/1597",
		"28563324/7985",
		"5575156/1597",
		2304,
		"5291460/1597",
		"512825/221",
		"18819463566/10157701",
		2461,
		3452,
		"3024075/1229",
		3425,
		2175
	],
	"edges": [
		[
			14,
			23
		],
		[
			8,
			14
		],
		[
			15,
			42
		],
		[
			15,
			55
		],
		[
			42,
			55
		],
		[
			7,
			45
		],
		[
			45,
			54
		],
		[
			7,
			54
		],
		[
			1,
			25
		],
		[
			25,
			32
		],
		[
			1,
			32
		],
		[
			4,
			45
		],
		[
			2,
			45
		],
		[
			2,
			4
		],
		[
			36,
			38
		],
		[
			30,
			36
		],
		[
			30,
			38
		],
		[
			26,
			38
		],
		[
			32,
			38
		],
		[
			26,
			32
		],
		[
			14,
			34
		],
		[
			8,
			34
		],
		[
			48,
			55
		],
		[
			38,
			55
		],
		[
			38,
			48
		],
		[
			15,
			57
		],
		[
			15,
			31
		],
		[
			31,
			57
		],
		[
			2,
			52
		],
		[
			44,
			50
		],
		[
			50,
			58
		],
		[
			44,
			58
		],
		[
			16,
			18
		],
		[
			14,
			18
		],
		[
			14,
			16
		],
		[
			11,
			49
		],
		[
			11,
			47
		],
		[
			9,
			13
		],
		[
			13,
			33
		],
		[
			9,
			33
		],
		[
			16,
			29
		],
		[
			18,
			29
		],
		[
			26,
			48
		],
		[
			26,
			49
		],
		[
			3,
			17
		],
		[
			3,
			35
		],
		[
			17,
			35
		],
		[
			4,
			54
		],
		[
			13,
			27
		],
		[
			7,
			27
		],
		[
			7,
			13
		],
		[
			54,
			56
		],
		[
			18,
			34
		],
		[
			37,
			38
		],
		[
			37,
			55
		],
		[
			2,
			10
		],
		[
			2,
			43
		],
		[
			10,
			43
		],
		[
			16,
			35
		],
		[
			14,
			35
		],
		[
			0,
			11
		],
		[
			11,
			25
		],
		[
			0,
			25
		],
		[
			30,
			50
		],
		[
			1,
			50
		],
		[
			1,
			30
		],
		[
			28,
			54
		],
		[
			20,
			27
		],
		[
			7,
			20
		],
		[
			6,
			10
		],
		[
			6,
			21
		],
		[
			5,
			12
		],
		[
			12,
			34
		],
		[
			5,
			34
		],
		[
			6,
			50
		],
		[
			1,
			6
		],
		[
			18,
			40
		],
		[
			5,
			40
		],
		[
			5,
			18
		],
		[
			33,
			54
		],
		[
			7,
			33
		],
		[
			22,
			58
		],
		[
			3,
			58
		],
		[
			3,
			22
		],
		[
			0,
			20
		],
		[
			0,
			24
		],
		[
			20,
			24
		],
		[
			29,
			40
		],
		[
			28,
			33
		],
		[
			7,
			24
		],
		[
			6,
			24
		],
		[
			6,
			7
		],
		[
			15,
			37
		],
		[
			15,
			40
		],
		[
			37,
			40
		],
		[
			30,
			32
		],
		[
			11,
			20
		],
		[
			36,
			37
		],
		[
			29,
			37
		],
		[
			29,
			36
		],
		[
			30,
			58
		],
		[
			34,
			41
		],
		[
			16,
			30
		],
		[
			16,
			58
		],
		[
			16,
			36
		],
		[
			1,
			24
		],
		[
			0,
			1
		],
		[
			3,
			16
		],
		[
			40,
			57
		],
		[
			21,
			50
		],
		[
			21,
			44
		],
		[
			7,
			43
		],
		[
			6,
			43
		],
		[
			5,
			46
		],
		[
			44,
			53
		],
		[
			11,
			39
		],
		[
			19,
			35
		],
		[
			14,
			19
		],
		[
			13,
			51
		],
		[
			46,
			57
		],
		[
			43,
			45
		],
		[
			20,
			39
		],
		[
			25,
			26
		],
		[
			11,
			26
		],
		[
			22,
			44
		],
		[
			5,
			57
		]
	],
	"score": 0.5125
}