{
	"content_type": "CG_SHOP_2025_Solution",
	"instance_uid": "simple-polygon-exterior-20_20_52abeef5",
	"steiner_points_x": [
		"9163956283/4040909",
		5681,
		"33419/4",
		5749,
		"57169/13",
		2307,
		1713,
		5516,
		"854177068/140233",
		"33414555319/7202401",
		6640,
		"119547079289/20711282",
		"70237059603/20711282",
		"13653940963/1872653",
		"52361423/6737",
		"91613639/13220",
		5173,
		7373,
		"16209/2",
		"109751125105/20711282",
		"48119915305/6151657",
		7133,
		"56419/10",
		"13686727/1853",
		7281,
		"25676389521731/3470026009",
		6225,
		5933,
		5585
	],
	"steiner_points_y": [
		"15397459872/4040909",
		1994,
		"8583/4",
		1567,
		"52724/13",
		3470,
		2590,
		2320,
		"228748099/140233",
		"20251220162/7202401",
		2812,
		"25244510783/20711282",
		"21975998137/20711282",
		"7816445544/1872653",
		"24912177/6737",
		"4358924/3305",
		1737,
		2092,
		"5625/2",
		"24595186359/20711282",
		"8638048783/6151657",
		3422,
		4199,
		"7442628/1853",
		3842,
		"14450250919584/3470026009",
		3743,
		3800,
		3857
	],
	"edges": [
		[
			9,
			14
		],
		[
			14,
			25
		],
		[
			30,
			37
		],
		[
			0,
			37
		],
		[
			0,
			30
		],
		[
			5,
			6
		],
		[
			5,
			43
		],
		[
			15,
			27
		],
		[
			27,
			29
		],
		[
			15,
			48
		],
		[
			9,
			15
		],
		[
			9,
			48
		],
		[
			20,
			25
		],
		[
			41,
			46
		],
		[
			44,
			46
		],
		[
			41,
			44
		],
		[
			10,
			26
		],
		[
			11,
			26
		],
		[
			13,
			26
		],
		[
			14,
			26
		],
		[
			47,
			48
		],
		[
			42,
			48
		],
		[
			42,
			47
		],
		[
			32,
			36
		],
		[
			36,
			39
		],
		[
			7,
			33
		],
		[
			33,
			43
		],
		[
			3,
			41
		],
		[
			4,
			41
		],
		[
			24,
			25
		],
		[
			12,
			26
		],
		[
			43,
			45
		],
		[
			29,
			36
		],
		[
			14,
			36
		],
		[
			0,
			28
		],
		[
			2,
			22
		],
		[
			3,
			22
		],
		[
			23,
			36
		],
		[
			23,
			39
		],
		[
			8,
			47
		],
		[
			4,
			44
		],
		[
			5,
			44
		],
		[
			4,
			5
		],
		[
			21,
			23
		],
		[
			21,
			28
		],
		[
			23,
			28
		],
		[
			0,
			18
		],
		[
			18,
			30
		],
		[
			16,
			47
		],
		[
			46,
			47
		],
		[
			16,
			46
		],
		[
			4,
			38
		],
		[
			4,
			34
		],
		[
			23,
			31
		],
		[
			25,
			26
		],
		[
			2,
			37
		],
		[
			3,
			37
		],
		[
			16,
			27
		],
		[
			27,
			36
		],
		[
			18,
			21
		],
		[
			5,
			7
		],
		[
			9,
			29
		],
		[
			19,
			23
		],
		[
			14,
			32
		],
		[
			15,
			47
		],
		[
			0,
			35
		],
		[
			7,
			46
		],
		[
			7,
			44
		],
		[
			5,
			34
		],
		[
			16,
			18
		],
		[
			18,
			27
		],
		[
			17,
			30
		],
		[
			17,
			41
		],
		[
			30,
			41
		],
		[
			37,
			40
		],
		[
			2,
			40
		],
		[
			3,
			30
		],
		[
			21,
			27
		],
		[
			21,
			36
		],
		[
			17,
			46
		],
		[
			9,
			24
		],
		[
			24,
			48
		],
		[
			3,
			38
		],
		[
			8,
			46
		],
		[
			35,
			37
		]
	],
	"score": 0.5166666666666667
}