{
	"content_type": "CG_SHOP_2025_Solution",
	"instance_uid": "simple-polygon-exterior-20_20_52abeef5",
	"steiner_points_x": [
		"70237059603/20711282",
		5681,
		"23948488170/4040909",
		5749,
		"57169/13",
		2307,
		7497,
		"119547079289/20711282",
		"12143/2",
		"33414555319/7202401",
		"33419/4",
		6379,
		6090,
		"49411222057/6151657",
		"52361423/6737",
		"91613639/13220",
		5173,
		7542,
		"1348537447/165610",
		"109751125105/20711282",
		5507,
		7133,
		"9163956283/4040909",
		"881647497/107413",
		"30140445868989/3557733386",
		1713,
		"13653940963/1872653",
		"13686727/1853",
		5894,
		7931,
		7282,
		7240,
		"25676389521731/3470026009"
	],
	"steiner_points_y": [
		"21975998137/20711282",
		1994,
		"17100235202/4040909",
		1567,
		"52724/13",
		3470,
		2541,
		"25244510783/20711282",
		1801,
		"20251220162/7202401",
		"8583/4",
		2314,
		3888,
		"8761478671/6151657",
		"24912177/6737",
		"4358924/3305",
		1737,
		2060,
		"448856391/165610",
		"24595186359/20711282",
		2274,
		3422,
		"15397459872/4040909",
		"186345358/107413",
		"6524382912741/3557733386",
		2590,
		"7816445544/1872653",
		"7442628/1853",
		3906,
		1736,
		3843,
		3857,
		"14450250919584/3470026009"
	],
	"edges": [
		[
			35,
			37
		],
		[
			37,
			49
		],
		[
			35,
			49
		],
		[
			13,
			45
		],
		[
			14,
			45
		],
		[
			3,
			30
		],
		[
			2,
			30
		],
		[
			21,
			23
		],
		[
			21,
			28
		],
		[
			23,
			28
		],
		[
			2,
			37
		],
		[
			3,
			37
		],
		[
			11,
			45
		],
		[
			12,
			45
		],
		[
			5,
			47
		],
		[
			5,
			7
		],
		[
			0,
			37
		],
		[
			0,
			35
		],
		[
			25,
			45
		],
		[
			14,
			25
		],
		[
			14,
			20
		],
		[
			20,
			36
		],
		[
			36,
			39
		],
		[
			21,
			40
		],
		[
			18,
			40
		],
		[
			18,
			21
		],
		[
			7,
			46
		],
		[
			46,
			47
		],
		[
			47,
			52
		],
		[
			4,
			41
		],
		[
			41,
			50
		],
		[
			4,
			50
		],
		[
			15,
			24
		],
		[
			24,
			48
		],
		[
			15,
			48
		],
		[
			26,
			41
		],
		[
			4,
			26
		],
		[
			43,
			49
		],
		[
			2,
			49
		],
		[
			43,
			44
		],
		[
			5,
			50
		],
		[
			7,
			50
		],
		[
			9,
			24
		],
		[
			24,
			25
		],
		[
			33,
			49
		],
		[
			33,
			43
		],
		[
			16,
			18
		],
		[
			16,
			40
		],
		[
			50,
			51
		],
		[
			7,
			51
		],
		[
			21,
			36
		],
		[
			36,
			40
		],
		[
			3,
			38
		],
		[
			4,
			5
		],
		[
			4,
			38
		],
		[
			10,
			45
		],
		[
			30,
			43
		],
		[
			4,
			34
		],
		[
			9,
			29
		],
		[
			9,
			14
		],
		[
			14,
			36
		],
		[
			29,
			36
		],
		[
			23,
			36
		],
		[
			5,
			34
		],
		[
			16,
			48
		],
		[
			18,
			31
		],
		[
			28,
			31
		],
		[
			16,
			32
		],
		[
			32,
			48
		],
		[
			5,
			6
		],
		[
			17,
			31
		],
		[
			17,
			26
		],
		[
			26,
			31
		],
		[
			22,
			48
		],
		[
			22,
			32
		],
		[
			25,
			42
		],
		[
			17,
			41
		],
		[
			8,
			51
		],
		[
			32,
			51
		],
		[
			41,
			51
		],
		[
			32,
			41
		],
		[
			23,
			39
		],
		[
			23,
			27
		],
		[
			8,
			32
		],
		[
			19,
			23
		],
		[
			9,
			15
		],
		[
			15,
			40
		],
		[
			29,
			40
		],
		[
			17,
			32
		],
		[
			31,
			37
		],
		[
			26,
			37
		],
		[
			3,
			26
		],
		[
			0,
			31
		],
		[
			0,
			28
		]
	],
	"score": 0.5147058823529411
}