{
	"content_type": "CG_SHOP_2025_Solution",
	"instance_uid": "cgshop2025_examples_ortho_80_f9b89ad1",
	"steiner_points_x": [
		410870,
		0,
		-142954,
		-138129,
		965979,
		343719,
		277047,
		258323,
		0,
		623768,
		623768,
		410870,
		623768,
		623768,
		780910,
		-229252,
		258323,
		-427958,
		-427958,
		42490,
		109569,
		109569,
		780910,
		-460837,
		258323,
		-141421,
		42490,
		1483686,
		1113820,
		1068424,
		1488886,
		1088607,
		2065894,
		1637165,
		2065895,
		965979,
		965979,
		-460837
	],
	"steiner_points_y": [
		-406910,
		729157,
		736220,
		697092,
		146309,
		-197839,
		-167798,
		556086,
		556086,
		-381338,
		284989,
		-489301,
		-489301,
		-406910,
		-388900,
		717105,
		767245,
		716274,
		717105,
		-301593,
		-301593,
		-267414,
		-489301,
		717105,
		977932,
		767245,
		-123585,
		330522,
		456258,
		319477,
		456258,
		235528,
		292621,
		146309,
		146309,
		292621,
		456258,
		556086
	],
	"edges": [
		[
			39,
			42
		],
		[
			40,
			42
		],
		[
			2,
			85
		],
		[
			2,
			26
		],
		[
			26,
			85
		],
		[
			21,
			93
		],
		[
			22,
			93
		],
		[
			80,
			93
		],
		[
			92,
			93
		],
		[
			80,
			92
		],
		[
			13,
			15
		],
		[
			107,
			110
		],
		[
			107,
			108
		],
		[
			111,
			115
		],
		[
			48,
			111
		],
		[
			45,
			116
		],
		[
			45,
			115
		],
		[
			87,
			88
		],
		[
			81,
			88
		],
		[
			81,
			87
		],
		[
			30,
			111
		],
		[
			31,
			111
		],
		[
			66,
			77
		],
		[
			77,
			95
		],
		[
			64,
			82
		],
		[
			82,
			83
		],
		[
			64,
			83
		],
		[
			45,
			109
		],
		[
			109,
			115
		],
		[
			3,
			5
		],
		[
			31,
			33
		],
		[
			26,
			52
		],
		[
			1,
			26
		],
		[
			1,
			52
		],
		[
			107,
			111
		],
		[
			31,
			107
		],
		[
			3,
			101
		],
		[
			6,
			101
		],
		[
			3,
			6
		],
		[
			19,
			21
		],
		[
			31,
			34
		],
		[
			45,
			47
		],
		[
			22,
			24
		],
		[
			22,
			94
		],
		[
			43,
			110
		],
		[
			10,
			99
		],
		[
			10,
			100
		],
		[
			13,
			86
		],
		[
			85,
			86
		],
		[
			13,
			85
		],
		[
			108,
			109
		],
		[
			80,
			91
		],
		[
			8,
			106
		],
		[
			9,
			106
		],
		[
			53,
			88
		],
		[
			39,
			112
		],
		[
			42,
			112
		],
		[
			25,
			93
		],
		[
			22,
			25
		],
		[
			107,
			109
		],
		[
			30,
			48
		],
		[
			43,
			112
		],
		[
			10,
			12
		],
		[
			9,
			101
		],
		[
			10,
			101
		],
		[
			34,
			107
		],
		[
			81,
			82
		],
		[
			81,
			83
		],
		[
			13,
			101
		],
		[
			86,
			101
		],
		[
			109,
			111
		],
		[
			66,
			83
		],
		[
			64,
			66
		],
		[
			26,
			28
		],
		[
			49,
			84
		],
		[
			28,
			84
		],
		[
			28,
			49
		],
		[
			29,
			84
		],
		[
			30,
			84
		],
		[
			28,
			90
		],
		[
			26,
			90
		],
		[
			36,
			114
		],
		[
			6,
			9
		],
		[
			18,
			80
		],
		[
			17,
			80
		],
		[
			77,
			79
		],
		[
			100,
			101
		],
		[
			73,
			75
		],
		[
			73,
			76
		],
		[
			73,
			97
		],
		[
			95,
			97
		],
		[
			73,
			95
		],
		[
			21,
			102
		],
		[
			36,
			38
		],
		[
			77,
			83
		],
		[
			16,
			80
		],
		[
			60,
			81
		],
		[
			81,
			105
		],
		[
			15,
			85
		],
		[
			15,
			26
		],
		[
			77,
			88
		],
		[
			79,
			88
		],
		[
			43,
			107
		],
		[
			53,
			79
		],
		[
			1,
			53
		],
		[
			1,
			79
		],
		[
			112,
			113
		],
		[
			43,
			113
		],
		[
			36,
			39
		],
		[
			48,
			84
		],
		[
			21,
			92
		],
		[
			16,
			25
		],
		[
			25,
			80
		],
		[
			69,
			97
		],
		[
			70,
			97
		],
		[
			97,
			98
		],
		[
			63,
			82
		],
		[
			59,
			96
		],
		[
			59,
			104
		],
		[
			83,
			88
		],
		[
			36,
			112
		],
		[
			68,
			103
		],
		[
			69,
			98
		],
		[
			69,
			103
		],
		[
			61,
			63
		],
		[
			60,
			96
		],
		[
			70,
			117
		],
		[
			70,
			73
		],
		[
			49,
			90
		],
		[
			82,
			105
		],
		[
			56,
			58
		],
		[
			56,
			59
		],
		[
			63,
			105
		],
		[
			81,
			96
		],
		[
			112,
			114
		],
		[
			70,
			72
		],
		[
			76,
			95
		],
		[
			16,
			89
		],
		[
			3,
			86
		],
		[
			52,
			90
		],
		[
			34,
			43
		],
		[
			2,
			86
		],
		[
			55,
			104
		],
		[
			56,
			104
		],
		[
			15,
			89
		]
	],
	"score": 0.5128205128205128
}