{
	"content_type": "CG_SHOP_2025_Solution",
	"instance_uid": "cgshop2025_examples_simple-polygon_40_986defab",
	"steiner_points_x": [
		6009,
		"2962401192/549791",
		7717,
		4539,
		4401,
		"12707609259/2453377",
		"11546/3",
		5568,
		"6640755346/917689",
		5613,
		3531,
		3577,
		"5443412909/706345",
		7072,
		"30288694743/4906754",
		"3578983762/1094645",
		3462,
		6870,
		5085,
		4665,
		7814,
		6192,
		"21896166063/4906754",
		3805,
		5846,
		2927,
		"3353088007/3596365",
		1484,
		"46360208018/5721041",
		1344,
		"6250194186/917689",
		5656,
		2415,
		6566,
		8139,
		"367324569/140821",
		2682,
		3322,
		6652,
		"19863665143/5143829",
		"3965400784/1094645",
		7618,
		5226,
		5099,
		5450,
		6226,
		4971,
		8398,
		4306,
		7378,
		5193,
		8311,
		4129,
		4172,
		6979,
		"18415749328/5143829",
		6648,
		"692784877/75073",
		3948,
		4644,
		"19079919046/5143829",
		"14631224667/3809173",
		"2608928976/2449417",
		"8432722541/2637601",
		"19687/3",
		"16306381779/2453377",
		5344,
		"4673163372/2449417",
		7663,
		1406,
		4470,
		3874,
		"29380783979/7618346",
		"3228203600/2449417"
	],
	"steiner_points_y": [
		5115,
		"1691476419/549791",
		1473,
		9505,
		7169,
		"24244244617/2453377",
		"20300/3",
		7728,
		"5676307371/917689",
		5660,
		8958,
		8368,
		"2601816447/706345",
		5619,
		"48539094179/4906754",
		"5039656736/1094645",
		4113,
		5387,
		5474,
		6839,
		2498,
		9364,
		"48451948283/4906754",
		9382,
		4997,
		8320,
		"27353850356/3596365",
		7490,
		"49221930506/5721041",
		4360,
		"5789655012/917689",
		3652,
		7574,
		8287,
		1631,
		"180464807/140821",
		7391,
		8024,
		9368,
		"42106020279/5143829",
		"4836433097/1094645",
		9220,
		9330,
		8944,
		8829,
		4814,
		5806,
		2298,
		9032,
		2539,
		7360,
		9323,
		6673,
		9597,
		5094,
		"39844761729/5143829",
		5748,
		"129786882/75073",
		"49346/5",
		3871,
		"40882017789/5143829",
		"25595315075/3809173",
		"10186386312/2449417",
		"3190718978/2637601",
		"5588/3",
		"24281613361/2453377",
		6439,
		"7326655473/2449417",
		2931,
		3872,
		8953,
		6813,
		"51925167525/7618346",
		"9328461096/2449417"
	],
	"edges": [
		[
			18,
			89
		],
		[
			89,
			104
		],
		[
			78,
			81
		],
		[
			33,
			78
		],
		[
			33,
			81
		],
		[
			89,
			108
		],
		[
			60,
			108
		],
		[
			60,
			89
		],
		[
			49,
			58
		],
		[
			58,
			86
		],
		[
			49,
			86
		],
		[
			17,
			89
		],
		[
			39,
			67
		],
		[
			0,
			67
		],
		[
			68,
			91
		],
		[
			68,
			81
		],
		[
			81,
			91
		],
		[
			74,
			87
		],
		[
			87,
			97
		],
		[
			74,
			97
		],
		[
			34,
			63
		],
		[
			50,
			63
		],
		[
			34,
			50
		],
		[
			17,
			108
		],
		[
			26,
			53
		],
		[
			27,
			53
		],
		[
			42,
			104
		],
		[
			19,
			42
		],
		[
			92,
			101
		],
		[
			5,
			92
		],
		[
			85,
			94
		],
		[
			57,
			85
		],
		[
			57,
			94
		],
		[
			6,
			58
		],
		[
			58,
			99
		],
		[
			6,
			99
		],
		[
			59,
			92
		],
		[
			59,
			86
		],
		[
			86,
			92
		],
		[
			25,
			94
		],
		[
			26,
			94
		],
		[
			32,
			81
		],
		[
			30,
			91
		],
		[
			31,
			91
		],
		[
			5,
			58
		],
		[
			58,
			64
		],
		[
			64,
			99
		],
		[
			23,
			60
		],
		[
			23,
			87
		],
		[
			60,
			87
		],
		[
			50,
			51
		],
		[
			2,
			50
		],
		[
			2,
			51
		],
		[
			53,
			96
		],
		[
			48,
			96
		],
		[
			48,
			53
		],
		[
			62,
			93
		],
		[
			93,
			98
		],
		[
			60,
			74
		],
		[
			73,
			81
		],
		[
			73,
			78
		],
		[
			53,
			57
		],
		[
			57,
			96
		],
		[
			65,
			72
		],
		[
			65,
			76
		],
		[
			72,
			76
		],
		[
			40,
			64
		],
		[
			49,
			64
		],
		[
			40,
			49
		],
		[
			63,
			93
		],
		[
			63,
			98
		],
		[
			24,
			94
		],
		[
			17,
			52
		],
		[
			52,
			108
		],
		[
			40,
			57
		],
		[
			40,
			96
		],
		[
			67,
			72
		],
		[
			0,
			72
		],
		[
			63,
			88
		],
		[
			50,
			88
		],
		[
			16,
			56
		],
		[
			6,
			56
		],
		[
			6,
			16
		],
		[
			17,
			24
		],
		[
			13,
			103
		],
		[
			73,
			84
		],
		[
			47,
			73
		],
		[
			47,
			84
		],
		[
			10,
			75
		],
		[
			11,
			75
		],
		[
			3,
			83
		],
		[
			83,
			84
		],
		[
			3,
			84
		],
		[
			37,
			66
		],
		[
			43,
			45
		],
		[
			43,
			62
		],
		[
			35,
			37
		],
		[
			35,
			65
		],
		[
			37,
			65
		],
		[
			55,
			69
		],
		[
			55,
			109
		],
		[
			69,
			109
		],
		[
			61,
			105
		],
		[
			54,
			61
		],
		[
			51,
			79
		],
		[
			56,
			107
		],
		[
			10,
			56
		],
		[
			56,
			80
		],
		[
			55,
			56
		],
		[
			28,
			49
		],
		[
			49,
			106
		],
		[
			28,
			106
		],
		[
			7,
			69
		],
		[
			8,
			69
		],
		[
			68,
			73
		],
		[
			111,
			112
		],
		[
			46,
			111
		],
		[
			3,
			44
		],
		[
			4,
			44
		],
		[
			16,
			99
		],
		[
			17,
			71
		],
		[
			24,
			71
		],
		[
			43,
			93
		],
		[
			21,
			74
		],
		[
			77,
			95
		],
		[
			77,
			100
		],
		[
			51,
			65
		],
		[
			35,
			51
		],
		[
			0,
			76
		],
		[
			66,
			67
		],
		[
			42,
			89
		],
		[
			3,
			47
		],
		[
			86,
			106
		],
		[
			65,
			77
		],
		[
			76,
			77
		],
		[
			35,
			50
		],
		[
			41,
			71
		],
		[
			47,
			90
		],
		[
			3,
			90
		],
		[
			9,
			69
		],
		[
			24,
			85
		],
		[
			43,
			82
		],
		[
			45,
			82
		],
		[
			1,
			76
		],
		[
			54,
			82
		],
		[
			20,
			42
		],
		[
			42,
			74
		],
		[
			20,
			74
		],
		[
			51,
			100
		],
		[
			28,
			90
		],
		[
			28,
			47
		],
		[
			82,
			83
		],
		[
			82,
			84
		],
		[
			3,
			110
		],
		[
			2,
			110
		],
		[
			26,
			57
		],
		[
			5,
			86
		],
		[
			44,
			111
		],
		[
			44,
			92
		],
		[
			92,
			111
		],
		[
			69,
			102
		],
		[
			43,
			83
		],
		[
			51,
			77
		],
		[
			43,
			88
		],
		[
			88,
			93
		],
		[
			61,
			73
		],
		[
			61,
			78
		],
		[
			78,
			105
		],
		[
			22,
			87
		],
		[
			61,
			82
		],
		[
			10,
			16
		],
		[
			90,
			106
		],
		[
			59,
			106
		],
		[
			59,
			90
		],
		[
			70,
			96
		],
		[
			28,
			96
		],
		[
			13,
			15
		],
		[
			40,
			85
		],
		[
			64,
			85
		],
		[
			29,
			73
		],
		[
			76,
			95
		],
		[
			41,
			99
		],
		[
			71,
			99
		],
		[
			37,
			72
		],
		[
			83,
			110
		],
		[
			32,
			91
		],
		[
			44,
			90
		],
		[
			37,
			67
		],
		[
			46,
			92
		],
		[
			56,
			109
		],
		[
			49,
			96
		],
		[
			4,
			111
		],
		[
			61,
			84
		],
		[
			29,
			47
		],
		[
			44,
			59
		],
		[
			23,
			108
		],
		[
			88,
			110
		],
		[
			2,
			88
		],
		[
			102,
			109
		],
		[
			109,
			113
		],
		[
			42,
			60
		],
		[
			10,
			13
		],
		[
			43,
			110
		],
		[
			71,
			85
		],
		[
			64,
			71
		],
		[
			107,
			109
		],
		[
			10,
			15
		]
	]
}