{
	"content_type": "CG_SHOP_2025_Solution",
	"instance_uid": "point-set_60_27bc003d",
	"steiner_points_x": [
		"10168/5",
		3630,
		2200,
		12192,
		3239,
		650,
		8700,
		3111,
		6806,
		2822,
		2898,
		"17956940/1769",
		11713,
		656,
		12654,
		3089,
		2420,
		164,
		"202966400/52093",
		12825,
		"122414911/17690",
		10700,
		9249,
		6828,
		"74329392/52093",
		10253,
		10253,
		"7364100/1601",
		"22200970/1769",
		"190045750/15529",
		6265,
		"20255180/1769"
	],
	"steiner_points_y": [
		"27088/5",
		9746,
		9359,
		1501,
		"4573/2",
		10460,
		8069,
		5750,
		1775,
		7730,
		7560,
		"53880/1769",
		900,
		8996,
		184,
		9772,
		10602,
		10274,
		"30177500/52093",
		6625,
		"109067/17690",
		5408,
		10672,
		1694,
		"364319972/52093",
		10677,
		10700,
		"60050/1601",
		"85790/1769",
		"125051700/15529",
		2829,
		"71160/1769"
	],
	"edges": [
		[
			12,
			66
		],
		[
			30,
			66
		],
		[
			12,
			30
		],
		[
			9,
			70
		],
		[
			7,
			70
		],
		[
			7,
			9
		],
		[
			1,
			57
		],
		[
			57,
			63
		],
		[
			1,
			63
		],
		[
			25,
			72
		],
		[
			22,
			72
		],
		[
			22,
			25
		],
		[
			10,
			91
		],
		[
			10,
			22
		],
		[
			22,
			91
		],
		[
			72,
			74
		],
		[
			22,
			74
		],
		[
			22,
			88
		],
		[
			65,
			73
		],
		[
			62,
			65
		],
		[
			62,
			73
		],
		[
			63,
			72
		],
		[
			63,
			74
		],
		[
			9,
			43
		],
		[
			9,
			12
		],
		[
			12,
			43
		],
		[
			41,
			63
		],
		[
			26,
			63
		],
		[
			36,
			74
		],
		[
			5,
			74
		],
		[
			12,
			37
		],
		[
			37,
			66
		],
		[
			20,
			81
		],
		[
			56,
			81
		],
		[
			20,
			56
		],
		[
			12,
			61
		],
		[
			12,
			47
		],
		[
			47,
			61
		],
		[
			69,
			70
		],
		[
			7,
			69
		],
		[
			33,
			54
		],
		[
			34,
			54
		],
		[
			33,
			34
		],
		[
			27,
			84
		],
		[
			27,
			60
		],
		[
			62,
			84
		],
		[
			65,
			77
		],
		[
			69,
			84
		],
		[
			62,
			69
		],
		[
			23,
			63
		],
		[
			23,
			72
		],
		[
			53,
			62
		],
		[
			49,
			62
		],
		[
			7,
			12
		],
		[
			7,
			47
		],
		[
			50,
			85
		],
		[
			66,
			85
		],
		[
			50,
			66
		],
		[
			8,
			28
		],
		[
			8,
			30
		],
		[
			28,
			30
		],
		[
			24,
			27
		],
		[
			24,
			60
		],
		[
			48,
			76
		],
		[
			53,
			76
		],
		[
			4,
			63
		],
		[
			34,
			38
		],
		[
			19,
			34
		],
		[
			19,
			38
		],
		[
			67,
			90
		],
		[
			12,
			67
		],
		[
			12,
			90
		],
		[
			47,
			69
		],
		[
			16,
			85
		],
		[
			40,
			64
		],
		[
			40,
			78
		],
		[
			62,
			75
		],
		[
			62,
			76
		],
		[
			75,
			76
		],
		[
			14,
			82
		],
		[
			0,
			82
		],
		[
			3,
			60
		],
		[
			3,
			64
		],
		[
			33,
			83
		],
		[
			54,
			83
		],
		[
			42,
			66
		],
		[
			30,
			42
		],
		[
			1,
			55
		],
		[
			1,
			39
		],
		[
			39,
			55
		],
		[
			17,
			77
		],
		[
			43,
			67
		],
		[
			70,
			84
		],
		[
			8,
			56
		],
		[
			28,
			56
		],
		[
			6,
			40
		],
		[
			10,
			25
		],
		[
			10,
			51
		],
		[
			25,
			51
		],
		[
			0,
			66
		],
		[
			29,
			66
		],
		[
			33,
			40
		],
		[
			33,
			64
		],
		[
			27,
			43
		],
		[
			43,
			84
		],
		[
			1,
			81
		],
		[
			1,
			90
		],
		[
			81,
			90
		],
		[
			39,
			83
		],
		[
			68,
			83
		],
		[
			39,
			68
		],
		[
			57,
			81
		],
		[
			19,
			87
		],
		[
			4,
			57
		],
		[
			17,
			65
		],
		[
			33,
			68
		],
		[
			15,
			66
		],
		[
			51,
			54
		],
		[
			51,
			80
		],
		[
			54,
			80
		],
		[
			11,
			66
		],
		[
			66,
			82
		],
		[
			11,
			82
		],
		[
			52,
			65
		],
		[
			35,
			65
		],
		[
			44,
			82
		],
		[
			6,
			19
		],
		[
			55,
			90
		],
		[
			8,
			12
		],
		[
			38,
			40
		],
		[
			6,
			38
		],
		[
			85,
			86
		],
		[
			33,
			38
		],
		[
			3,
			90
		],
		[
			3,
			67
		],
		[
			42,
			85
		],
		[
			2,
			85
		],
		[
			2,
			42
		],
		[
			1,
			54
		],
		[
			1,
			51
		],
		[
			28,
			79
		],
		[
			28,
			32
		],
		[
			32,
			79
		],
		[
			42,
			79
		],
		[
			42,
			89
		],
		[
			39,
			54
		],
		[
			22,
			36
		],
		[
			47,
			62
		],
		[
			31,
			42
		],
		[
			13,
			42
		],
		[
			20,
			28
		],
		[
			20,
			79
		],
		[
			12,
			56
		],
		[
			3,
			24
		],
		[
			24,
			45
		],
		[
			3,
			45
		],
		[
			27,
			67
		],
		[
			51,
			71
		],
		[
			10,
			71
		],
		[
			43,
			70
		],
		[
			27,
			45
		],
		[
			56,
			90
		],
		[
			32,
			42
		],
		[
			45,
			67
		],
		[
			49,
			65
		],
		[
			47,
			75
		],
		[
			46,
			75
		],
		[
			21,
			75
		],
		[
			55,
			68
		],
		[
			20,
			57
		],
		[
			57,
			79
		],
		[
			59,
			61
		],
		[
			21,
			61
		],
		[
			1,
			23
		],
		[
			68,
			90
		],
		[
			23,
			51
		],
		[
			18,
			63
		],
		[
			64,
			90
		],
		[
			30,
			32
		],
		[
			46,
			76
		],
		[
			5,
			63
		],
		[
			12,
			59
		],
		[
			23,
			25
		],
		[
			61,
			75
		],
		[
			33,
			90
		]
	],
	"score": 0.003927583605639475
}