{
	"content_type": "CG_SHOP_2025_Solution",
	"instance_uid": "cgshop2025_examples_ortho_250_d9594e89",
	"steiner_points_x": [],
	"steiner_points_y": [],
	"edges": [
		[
			6,
			17
		],
		[
			6,
			20
		],
		[
			17,
			20
		],
		[
			242,
			244
		],
		[
			242,
			245
		],
		[
			149,
			151
		],
		[
			135,
			137
		],
		[
			135,
			138
		],
		[
			6,
			21
		],
		[
			138,
			140
		],
		[
			246,
			248
		],
		[
			246,
			249
		],
		[
			132,
			134
		],
		[
			142,
			145
		],
		[
			143,
			145
		],
		[
			225,
			228
		],
		[
			225,
			230
		],
		[
			228,
			230
		],
		[
			135,
			140
		],
		[
			135,
			141
		],
		[
			49,
			56
		],
		[
			52,
			56
		],
		[
			49,
			52
		],
		[
			2,
			4
		],
		[
			2,
			5
		],
		[
			142,
			146
		],
		[
			11,
			14
		],
		[
			11,
			16
		],
		[
			14,
			16
		],
		[
			23,
			26
		],
		[
			23,
			29
		],
		[
			26,
			29
		],
		[
			168,
			170
		],
		[
			37,
			43
		],
		[
			41,
			43
		],
		[
			37,
			41
		],
		[
			146,
			148
		],
		[
			56,
			72
		],
		[
			43,
			56
		],
		[
			43,
			72
		],
		[
			149,
			152
		],
		[
			87,
			89
		],
		[
			87,
			92
		],
		[
			89,
			92
		],
		[
			43,
			47
		],
		[
			44,
			47
		],
		[
			148,
			152
		],
		[
			148,
			153
		],
		[
			47,
			56
		],
		[
			47,
			49
		],
		[
			158,
			160
		],
		[
			106,
			162
		],
		[
			106,
			163
		],
		[
			61,
			68
		],
		[
			61,
			71
		],
		[
			68,
			71
		],
		[
			118,
			155
		],
		[
			118,
			156
		],
		[
			56,
			60
		],
		[
			58,
			60
		],
		[
			56,
			58
		],
		[
			115,
			157
		],
		[
			115,
			158
		],
		[
			60,
			72
		],
		[
			158,
			161
		],
		[
			78,
			94
		],
		[
			83,
			94
		],
		[
			78,
			83
		],
		[
			171,
			173
		],
		[
			61,
			64
		],
		[
			61,
			67
		],
		[
			64,
			67
		],
		[
			165,
			167
		],
		[
			171,
			174
		],
		[
			95,
			102
		],
		[
			95,
			104
		],
		[
			102,
			104
		],
		[
			165,
			168
		],
		[
			73,
			77
		],
		[
			74,
			77
		],
		[
			108,
			111
		],
		[
			108,
			114
		],
		[
			111,
			114
		],
		[
			104,
			163
		],
		[
			105,
			163
		],
		[
			119,
			122
		],
		[
			119,
			124
		],
		[
			122,
			124
		],
		[
			175,
			180
		],
		[
			176,
			180
		],
		[
			106,
			161
		],
		[
			107,
			161
		],
		[
			177,
			179
		],
		[
			87,
			94
		],
		[
			83,
			87
		],
		[
			134,
			141
		],
		[
			132,
			141
		],
		[
			188,
			190
		],
		[
			92,
			94
		],
		[
			177,
			180
		],
		[
			224,
			230
		],
		[
			11,
			13
		],
		[
			174,
			180
		],
		[
			125,
			132
		],
		[
			126,
			132
		],
		[
			114,
			158
		],
		[
			187,
			190
		],
		[
			95,
			97
		],
		[
			95,
			100
		],
		[
			97,
			100
		],
		[
			100,
			102
		],
		[
			240,
			245
		],
		[
			241,
			245
		],
		[
			7,
			9
		],
		[
			17,
			19
		],
		[
			190,
			192
		],
		[
			171,
			180
		],
		[
			6,
			9
		],
		[
			126,
			131
		],
		[
			181,
			183
		],
		[
			168,
			180
		],
		[
			170,
			180
		],
		[
			9,
			17
		],
		[
			10,
			17
		],
		[
			184,
			186
		],
		[
			104,
			164
		],
		[
			10,
			16
		],
		[
			168,
			181
		],
		[
			125,
			153
		],
		[
			132,
			153
		],
		[
			34,
			36
		],
		[
			84,
			86
		],
		[
			192,
			194
		],
		[
			198,
			232
		],
		[
			198,
			233
		],
		[
			206,
			211
		],
		[
			207,
			211
		],
		[
			1,
			249
		],
		[
			38,
			40
		],
		[
			187,
			192
		],
		[
			187,
			195
		],
		[
			192,
			195
		],
		[
			199,
			223
		],
		[
			221,
			223
		],
		[
			199,
			221
		],
		[
			23,
			25
		],
		[
			74,
			76
		],
		[
			202,
			214
		],
		[
			202,
			215
		],
		[
			81,
			83
		],
		[
			186,
			197
		],
		[
			187,
			197
		],
		[
			199,
			232
		],
		[
			78,
			81
		],
		[
			199,
			219
		],
		[
			200,
			219
		],
		[
			32,
			186
		],
		[
			33,
			186
		],
		[
			125,
			154
		],
		[
			22,
			29
		],
		[
			202,
			219
		],
		[
			200,
			202
		],
		[
			79,
			81
		],
		[
			202,
			211
		],
		[
			211,
			214
		],
		[
			238,
			245
		],
		[
			239,
			245
		],
		[
			26,
			28
		],
		[
			195,
			197
		],
		[
			6,
			30
		],
		[
			21,
			30
		],
		[
			203,
			211
		],
		[
			203,
			206
		],
		[
			97,
			99
		],
		[
			33,
			36
		],
		[
			33,
			37
		],
		[
			207,
			210
		],
		[
			215,
			219
		],
		[
			33,
			73
		],
		[
			37,
			73
		],
		[
			83,
			86
		],
		[
			223,
			232
		],
		[
			165,
			181
		],
		[
			186,
			198
		],
		[
			30,
			32
		],
		[
			235,
			246
		],
		[
			235,
			249
		],
		[
			37,
			72
		],
		[
			37,
			40
		],
		[
			203,
			205
		],
		[
			33,
			184
		],
		[
			73,
			184
		],
		[
			89,
			91
		],
		[
			224,
			232
		],
		[
			94,
			184
		],
		[
			95,
			184
		],
		[
			107,
			158
		],
		[
			207,
			209
		],
		[
			238,
			246
		],
		[
			49,
			51
		],
		[
			73,
			94
		],
		[
			141,
			153
		],
		[
			32,
			198
		],
		[
			32,
			233
		],
		[
			211,
			213
		],
		[
			235,
			238
		],
		[
			44,
			46
		],
		[
			234,
			249
		],
		[
			1,
			234
		],
		[
			142,
			153
		],
		[
			1,
			30
		],
		[
			1,
			32
		],
		[
			1,
			233
		],
		[
			118,
			125
		],
		[
			119,
			125
		],
		[
			128,
			131
		],
		[
			129,
			131
		],
		[
			215,
			218
		],
		[
			216,
			218
		],
		[
			52,
			55
		],
		[
			21,
			29
		],
		[
			219,
			221
		],
		[
			5,
			30
		],
		[
			95,
			164
		],
		[
			142,
			148
		],
		[
			111,
			113
		],
		[
			2,
			30
		],
		[
			117,
			156
		],
		[
			53,
			55
		],
		[
			108,
			110
		],
		[
			61,
			72
		],
		[
			119,
			121
		],
		[
			225,
			227
		],
		[
			224,
			231
		],
		[
			77,
			94
		],
		[
			115,
			156
		],
		[
			235,
			237
		],
		[
			164,
			183
		],
		[
			95,
			183
		],
		[
			115,
			117
		],
		[
			108,
			158
		],
		[
			62,
			64
		],
		[
			164,
			181
		],
		[
			118,
			154
		],
		[
			65,
			67
		],
		[
			126,
			128
		],
		[
			68,
			70
		]
	]
}