{
	"content_type": "CG_SHOP_2025_Solution",
	"instance_uid": "simple-polygon_250_c02755d7",
	"steiner_points_x": [
		"62865967/20417",
		"2934857/4229",
		2316,
		"8568681/5597",
		664,
		1539,
		1588,
		362,
		"17477261/7466",
		394,
		676,
		394,
		"534397/6994",
		480,
		213,
		"22691202/37265",
		"6608272/2897",
		"11196169/14309",
		"1626900/653",
		2835,
		2711,
		480,
		2287,
		278,
		1750,
		"897093863/300977",
		"685/2",
		"1751322/1105",
		692,
		2273,
		362,
		"25450263/31237",
		2338,
		"22691202/37265",
		"1728072/1105",
		2273,
		2345,
		822,
		2316,
		205,
		"80931360/36749",
		"980576029/328645",
		"603/2",
		"83509113/57901",
		"110092656/118213",
		403,
		"178078486/216481",
		394,
		"5722231/8458",
		619,
		1572,
		2150,
		1420,
		"514071623/171257",
		"6218917/95642",
		"1074409593/380357",
		368,
		"27902337/18965",
		"7964137/3497",
		"255917520/106409",
		"361081709/131557",
		"3210079/3770",
		"6746631/12181",
		2370,
		"15377465/6994",
		1414,
		1414,
		1752,
		1535,
		"8647263/3733",
		361,
		1577,
		1638,
		1289,
		1033,
		1133,
		2328,
		1864,
		2294,
		1258,
		1551,
		"1705659/1105",
		1422,
		1755,
		686,
		683
	],
	"steiner_points_y": [
		"55477099/20417",
		"2165120/4229",
		2706,
		"873483/5597",
		238,
		2922,
		2921,
		1217,
		"4797049/7466",
		349,
		530,
		1213,
		"19007187/6994",
		2544,
		1213,
		"102157201/37265",
		"9110716/2897",
		"2529890/14309",
		"199031/653",
		1213,
		3702,
		1213,
		2206,
		2649,
		3907,
		"1103626210/300977",
		2544,
		"4434539/1105",
		234,
		158,
		1213,
		"88399663/31237",
		2575,
		"52557486/37265",
		"4425539/1105",
		142,
		3465,
		207,
		1569,
		3938,
		"7875315/36749",
		"134089422/328645",
		"15019/4",
		"104157837/57901",
		"307271130/118213",
		478,
		"41001357/216481",
		1217,
		"4487087/8458",
		3272,
		3984,
		3785,
		3316,
		"255232404/171257",
		"7522833/95642",
		"841675953/380357",
		2638,
		"30233416/18965",
		"5641332/3497",
		"150696497/106409",
		"350515649/131557",
		"3501157/3770",
		"8770020/12181",
		2854,
		"10801799/6994",
		3333,
		3316,
		1011,
		2720,
		"2192295/3733",
		352,
		3896,
		2518,
		1938,
		1611,
		1379,
		2960,
		3785,
		1821,
		927,
		3978,
		"4416863/1105",
		3319,
		3825,
		1631,
		2887
	],
	"edges": [
		[
			244,
			329
		],
		[
			245,
			329
		],
		[
			244,
			245
		],
		[
			227,
			287
		],
		[
			228,
			287
		],
		[
			227,
			228
		],
		[
			6,
			249
		],
		[
			1,
			6
		],
		[
			1,
			249
		],
		[
			133,
			276
		],
		[
			133,
			263
		],
		[
			263,
			276
		],
		[
			242,
			329
		],
		[
			243,
			329
		],
		[
			242,
			243
		],
		[
			28,
			30
		],
		[
			29,
			30
		],
		[
			28,
			29
		],
		[
			247,
			248
		],
		[
			10,
			247
		],
		[
			10,
			248
		],
		[
			221,
			231
		],
		[
			221,
			232
		],
		[
			231,
			232
		],
		[
			15,
			31
		],
		[
			15,
			32
		],
		[
			31,
			32
		],
		[
			217,
			320
		],
		[
			218,
			320
		],
		[
			217,
			218
		],
		[
			24,
			291
		],
		[
			24,
			28
		],
		[
			28,
			291
		],
		[
			24,
			30
		],
		[
			260,
			298
		],
		[
			236,
			260
		],
		[
			236,
			298
		],
		[
			90,
			250
		],
		[
			89,
			90
		],
		[
			89,
			250
		],
		[
			243,
			244
		],
		[
			228,
			229
		],
		[
			228,
			278
		],
		[
			229,
			278
		],
		[
			15,
			290
		],
		[
			15,
			17
		],
		[
			17,
			290
		],
		[
			316,
			332
		],
		[
			302,
			332
		],
		[
			302,
			316
		],
		[
			15,
			21
		],
		[
			15,
			268
		],
		[
			21,
			268
		],
		[
			224,
			278
		],
		[
			224,
			228
		],
		[
			274,
			300
		],
		[
			274,
			321
		],
		[
			300,
			321
		],
		[
			233,
			234
		],
		[
			233,
			260
		],
		[
			234,
			260
		],
		[
			15,
			23
		],
		[
			23,
			31
		],
		[
			168,
			255
		],
		[
			178,
			255
		],
		[
			168,
			178
		],
		[
			247,
			317
		],
		[
			246,
			247
		],
		[
			246,
			317
		],
		[
			11,
			247
		],
		[
			10,
			11
		],
		[
			24,
			26
		],
		[
			26,
			291
		],
		[
			84,
			252
		],
		[
			83,
			84
		],
		[
			83,
			252
		],
		[
			11,
			317
		],
		[
			179,
			255
		],
		[
			255,
			318
		],
		[
			179,
			318
		],
		[
			87,
			91
		],
		[
			88,
			91
		],
		[
			87,
			88
		],
		[
			15,
			279
		],
		[
			17,
			279
		],
		[
			236,
			312
		],
		[
			213,
			236
		],
		[
			213,
			312
		],
		[
			232,
			295
		],
		[
			233,
			295
		],
		[
			232,
			233
		],
		[
			128,
			262
		],
		[
			129,
			262
		],
		[
			128,
			129
		],
		[
			131,
			273
		],
		[
			273,
			276
		],
		[
			131,
			276
		],
		[
			24,
			25
		],
		[
			25,
			26
		],
		[
			14,
			32
		],
		[
			14,
			33
		],
		[
			32,
			33
		],
		[
			230,
			254
		],
		[
			231,
			254
		],
		[
			230,
			231
		],
		[
			259,
			320
		],
		[
			295,
			320
		],
		[
			259,
			295
		],
		[
			230,
			278
		],
		[
			229,
			230
		],
		[
			196,
			197
		],
		[
			196,
			204
		],
		[
			197,
			204
		],
		[
			225,
			287
		],
		[
			287,
			296
		],
		[
			225,
			296
		],
		[
			122,
			138
		],
		[
			123,
			138
		],
		[
			122,
			123
		],
		[
			239,
			311
		],
		[
			241,
			311
		],
		[
			239,
			241
		],
		[
			104,
			274
		],
		[
			105,
			274
		],
		[
			104,
			105
		],
		[
			228,
			267
		],
		[
			225,
			228
		],
		[
			225,
			267
		],
		[
			218,
			259
		],
		[
			12,
			33
		],
		[
			13,
			33
		],
		[
			12,
			13
		],
		[
			23,
			30
		],
		[
			30,
			31
		],
		[
			254,
			278
		],
		[
			61,
			288
		],
		[
			62,
			288
		],
		[
			61,
			62
		],
		[
			59,
			314
		],
		[
			60,
			314
		],
		[
			59,
			60
		],
		[
			48,
			55
		],
		[
			48,
			56
		],
		[
			55,
			56
		],
		[
			64,
			66
		],
		[
			66,
			269
		],
		[
			64,
			269
		],
		[
			63,
			288
		],
		[
			62,
			63
		],
		[
			122,
			139
		],
		[
			138,
			139
		],
		[
			271,
			297
		],
		[
			204,
			297
		],
		[
			204,
			271
		],
		[
			261,
			297
		],
		[
			261,
			271
		],
		[
			186,
			187
		],
		[
			186,
			188
		],
		[
			187,
			188
		],
		[
			174,
			175
		],
		[
			174,
			176
		],
		[
			175,
			176
		],
		[
			51,
			293
		],
		[
			51,
			53
		],
		[
			53,
			293
		],
		[
			119,
			299
		],
		[
			122,
			299
		],
		[
			119,
			122
		],
		[
			214,
			295
		],
		[
			214,
			320
		],
		[
			300,
			330
		],
		[
			321,
			330
		],
		[
			57,
			328
		],
		[
			58,
			328
		],
		[
			57,
			58
		],
		[
			180,
			182
		],
		[
			180,
			183
		],
		[
			182,
			183
		],
		[
			96,
			286
		],
		[
			270,
			286
		],
		[
			96,
			270
		],
		[
			288,
			308
		],
		[
			60,
			288
		],
		[
			60,
			308
		],
		[
			101,
			286
		],
		[
			286,
			301
		],
		[
			101,
			301
		],
		[
			226,
			287
		],
		[
			226,
			227
		],
		[
			173,
			176
		],
		[
			173,
			174
		],
		[
			50,
			53
		],
		[
			50,
			54
		],
		[
			53,
			54
		],
		[
			42,
			307
		],
		[
			43,
			307
		],
		[
			42,
			43
		],
		[
			173,
			177
		],
		[
			176,
			177
		],
		[
			172,
			177
		],
		[
			172,
			178
		],
		[
			177,
			178
		],
		[
			284,
			300
		],
		[
			284,
			330
		],
		[
			73,
			288
		],
		[
			63,
			73
		],
		[
			49,
			54
		],
		[
			49,
			55
		],
		[
			54,
			55
		],
		[
			226,
			296
		],
		[
			51,
			52
		],
		[
			52,
			293
		],
		[
			45,
			323
		],
		[
			46,
			323
		],
		[
			45,
			46
		],
		[
			181,
			294
		],
		[
			182,
			294
		],
		[
			181,
			182
		],
		[
			214,
			217
		],
		[
			163,
			322
		],
		[
			48,
			163
		],
		[
			48,
			322
		],
		[
			185,
			190
		],
		[
			186,
			190
		],
		[
			185,
			186
		],
		[
			124,
			265
		],
		[
			124,
			134
		],
		[
			134,
			265
		],
		[
			212,
			312
		],
		[
			212,
			236
		],
		[
			207,
			325
		],
		[
			208,
			325
		],
		[
			207,
			208
		],
		[
			87,
			92
		],
		[
			91,
			92
		],
		[
			191,
			192
		],
		[
			191,
			206
		],
		[
			192,
			206
		],
		[
			79,
			81
		],
		[
			79,
			305
		],
		[
			81,
			305
		],
		[
			41,
			210
		],
		[
			41,
			211
		],
		[
			210,
			211
		],
		[
			79,
			80
		],
		[
			80,
			81
		],
		[
			125,
			306
		],
		[
			125,
			133
		],
		[
			133,
			306
		],
		[
			168,
			170
		],
		[
			168,
			171
		],
		[
			170,
			171
		],
		[
			223,
			278
		],
		[
			223,
			254
		],
		[
			165,
			256
		],
		[
			167,
			256
		],
		[
			165,
			167
		],
		[
			324,
			325
		],
		[
			207,
			324
		],
		[
			18,
			279
		],
		[
			279,
			285
		],
		[
			18,
			285
		],
		[
			184,
			324
		],
		[
			191,
			324
		],
		[
			184,
			191
		],
		[
			90,
			91
		],
		[
			88,
			90
		],
		[
			50,
			51
		],
		[
			87,
			310
		],
		[
			93,
			310
		],
		[
			87,
			93
		],
		[
			172,
			173
		],
		[
			255,
			256
		],
		[
			256,
			318
		],
		[
			126,
			306
		],
		[
			125,
			126
		],
		[
			95,
			155
		],
		[
			152,
			155
		],
		[
			95,
			152
		],
		[
			191,
			207
		],
		[
			94,
			155
		],
		[
			94,
			95
		],
		[
			206,
			207
		],
		[
			92,
			93
		],
		[
			77,
			78
		],
		[
			77,
			79
		],
		[
			78,
			79
		],
		[
			313,
			326
		],
		[
			86,
			326
		],
		[
			86,
			313
		],
		[
			236,
			295
		],
		[
			233,
			236
		],
		[
			145,
			146
		],
		[
			145,
			147
		],
		[
			146,
			147
		],
		[
			164,
			318
		],
		[
			165,
			318
		],
		[
			164,
			165
		],
		[
			79,
			82
		],
		[
			82,
			305
		],
		[
			236,
			237
		],
		[
			212,
			237
		],
		[
			232,
			259
		],
		[
			308,
			314
		],
		[
			43,
			324
		],
		[
			44,
			324
		],
		[
			43,
			44
		],
		[
			206,
			334
		],
		[
			192,
			334
		],
		[
			138,
			335
		],
		[
			137,
			138
		],
		[
			137,
			335
		],
		[
			41,
			324
		],
		[
			41,
			325
		],
		[
			136,
			335
		],
		[
			136,
			137
		],
		[
			159,
			313
		],
		[
			159,
			326
		],
		[
			135,
			281
		],
		[
			136,
			281
		],
		[
			135,
			136
		],
		[
			143,
			315
		],
		[
			315,
			321
		],
		[
			143,
			321
		],
		[
			124,
			133
		],
		[
			133,
			265
		],
		[
			171,
			178
		],
		[
			171,
			172
		],
		[
			14,
			15
		],
		[
			148,
			149
		],
		[
			148,
			150
		],
		[
			149,
			150
		],
		[
			155,
			326
		],
		[
			86,
			155
		],
		[
			163,
			164
		],
		[
			164,
			322
		],
		[
			36,
			319
		],
		[
			37,
			319
		],
		[
			36,
			37
		],
		[
			160,
			313
		],
		[
			159,
			160
		],
		[
			123,
			335
		],
		[
			34,
			258
		],
		[
			35,
			258
		],
		[
			34,
			35
		],
		[
			112,
			114
		],
		[
			114,
			289
		],
		[
			112,
			289
		],
		[
			127,
			130
		],
		[
			127,
			273
		],
		[
			130,
			273
		],
		[
			35,
			319
		],
		[
			35,
			36
		],
		[
			118,
			299
		],
		[
			118,
			119
		],
		[
			210,
			325
		],
		[
			21,
			22
		],
		[
			22,
			268
		],
		[
			86,
			93
		],
		[
			86,
			94
		],
		[
			93,
			94
		],
		[
			39,
			317
		],
		[
			11,
			39
		],
		[
			104,
			327
		],
		[
			327,
			333
		],
		[
			104,
			333
		],
		[
			109,
			115
		],
		[
			109,
			116
		],
		[
			115,
			116
		],
		[
			111,
			112
		],
		[
			111,
			292
		],
		[
			112,
			292
		],
		[
			76,
			272
		],
		[
			77,
			272
		],
		[
			76,
			77
		],
		[
			219,
			259
		],
		[
			218,
			219
		],
		[
			222,
			254
		],
		[
			221,
			222
		],
		[
			221,
			254
		],
		[
			128,
			130
		],
		[
			130,
			262
		],
		[
			258,
			319
		],
		[
			83,
			282
		],
		[
			252,
			282
		],
		[
			156,
			326
		],
		[
			157,
			326
		],
		[
			156,
			157
		],
		[
			120,
			122
		],
		[
			121,
			122
		],
		[
			120,
			121
		],
		[
			270,
			275
		],
		[
			100,
			270
		],
		[
			100,
			275
		],
		[
			114,
			292
		],
		[
			19,
			279
		],
		[
			19,
			285
		],
		[
			111,
			115
		],
		[
			115,
			292
		],
		[
			96,
			97
		],
		[
			96,
			98
		],
		[
			97,
			98
		],
		[
			127,
			128
		],
		[
			272,
			282
		],
		[
			82,
			282
		],
		[
			82,
			272
		],
		[
			245,
			317
		],
		[
			245,
			246
		],
		[
			106,
			274
		],
		[
			105,
			106
		],
		[
			113,
			114
		],
		[
			113,
			289
		],
		[
			98,
			270
		],
		[
			98,
			275
		],
		[
			23,
			268
		],
		[
			15,
			19
		],
		[
			15,
			20
		],
		[
			19,
			20
		],
		[
			41,
			317
		],
		[
			40,
			41
		],
		[
			40,
			317
		],
		[
			213,
			295
		],
		[
			216,
			217
		],
		[
			214,
			216
		],
		[
			23,
			24
		],
		[
			39,
			40
		],
		[
			148,
			286
		],
		[
			150,
			286
		],
		[
			321,
			333
		],
		[
			144,
			333
		],
		[
			144,
			321
		],
		[
			160,
			252
		],
		[
			84,
			160
		],
		[
			1,
			253
		],
		[
			6,
			253
		],
		[
			330,
			331
		],
		[
			107,
			330
		],
		[
			107,
			331
		],
		[
			124,
			125
		],
		[
			58,
			308
		],
		[
			58,
			288
		],
		[
			0,
			249
		],
		[
			0,
			1
		],
		[
			194,
			205
		],
		[
			196,
			205
		],
		[
			194,
			196
		],
		[
			13,
			14
		],
		[
			117,
			139
		],
		[
			139,
			299
		],
		[
			117,
			299
		],
		[
			134,
			335
		],
		[
			134,
			136
		],
		[
			109,
			110
		],
		[
			109,
			111
		],
		[
			110,
			111
		],
		[
			109,
			140
		],
		[
			116,
			140
		],
		[
			274,
			277
		],
		[
			277,
			300
		],
		[
			147,
			301
		],
		[
			147,
			327
		],
		[
			301,
			327
		],
		[
			211,
			311
		],
		[
			211,
			329
		],
		[
			311,
			329
		],
		[
			148,
			301
		],
		[
			241,
			329
		],
		[
			241,
			242
		],
		[
			107,
			321
		],
		[
			49,
			50
		],
		[
			95,
			151
		],
		[
			151,
			152
		],
		[
			84,
			85
		],
		[
			84,
			313
		],
		[
			85,
			313
		],
		[
			38,
			39
		],
		[
			11,
			38
		],
		[
			194,
			334
		],
		[
			205,
			334
		],
		[
			277,
			284
		],
		[
			147,
			148
		],
		[
			284,
			331
		],
		[
			107,
			140
		],
		[
			107,
			109
		],
		[
			155,
			156
		],
		[
			211,
			317
		],
		[
			317,
			329
		],
		[
			1,
			3
		],
		[
			3,
			253
		],
		[
			106,
			277
		],
		[
			123,
			124
		],
		[
			123,
			134
		],
		[
			5,
			253
		],
		[
			3,
			5
		],
		[
			161,
			252
		],
		[
			160,
			161
		],
		[
			152,
			153
		],
		[
			153,
			155
		],
		[
			134,
			281
		],
		[
			41,
			43
		],
		[
			47,
			322
		],
		[
			47,
			48
		],
		[
			1,
			2
		],
		[
			2,
			3
		],
		[
			107,
			108
		],
		[
			108,
			109
		],
		[
			4,
			5
		],
		[
			3,
			4
		],
		[
			117,
			118
		],
		[
			194,
			195
		],
		[
			195,
			196
		],
		[
			220,
			232
		],
		[
			220,
			221
		],
		[
			186,
			189
		],
		[
			189,
			190
		],
		[
			142,
			315
		],
		[
			142,
			143
		],
		[
			239,
			240
		],
		[
			240,
			241
		],
		[
			145,
			333
		],
		[
			147,
			333
		],
		[
			7,
			248
		],
		[
			9,
			248
		],
		[
			7,
			9
		],
		[
			178,
			179
		],
		[
			101,
			270
		],
		[
			100,
			101
		],
		[
			193,
			334
		],
		[
			193,
			194
		],
		[
			68,
			70
		],
		[
			68,
			303
		],
		[
			70,
			303
		],
		[
			203,
			204
		],
		[
			203,
			271
		],
		[
			183,
			323
		],
		[
			184,
			323
		],
		[
			183,
			184
		],
		[
			6,
			248
		],
		[
			6,
			7
		],
		[
			102,
			327
		],
		[
			103,
			327
		],
		[
			102,
			103
		],
		[
			132,
			133
		],
		[
			132,
			263
		],
		[
			180,
			318
		],
		[
			318,
			322
		],
		[
			180,
			322
		],
		[
			119,
			120
		],
		[
			162,
			272
		],
		[
			162,
			282
		],
		[
			37,
			38
		],
		[
			11,
			37
		],
		[
			142,
			332
		],
		[
			315,
			332
		],
		[
			116,
			117
		],
		[
			116,
			139
		],
		[
			68,
			69
		],
		[
			69,
			70
		],
		[
			220,
			259
		],
		[
			184,
			185
		],
		[
			184,
			190
		],
		[
			102,
			301
		],
		[
			197,
			297
		],
		[
			198,
			257
		],
		[
			198,
			297
		],
		[
			257,
			297
		],
		[
			64,
			67
		],
		[
			66,
			67
		],
		[
			64,
			72
		],
		[
			67,
			72
		],
		[
			200,
			201
		],
		[
			200,
			202
		],
		[
			201,
			202
		],
		[
			274,
			333
		],
		[
			190,
			191
		],
		[
			142,
			302
		],
		[
			33,
			319
		],
		[
			33,
			37
		],
		[
			56,
			328
		],
		[
			56,
			57
		],
		[
			196,
			283
		],
		[
			204,
			283
		],
		[
			139,
			140
		],
		[
			315,
			316
		],
		[
			234,
			235
		],
		[
			234,
			251
		],
		[
			235,
			251
		],
		[
			67,
			71
		],
		[
			71,
			72
		],
		[
			65,
			66
		],
		[
			65,
			269
		],
		[
			140,
			141
		],
		[
			107,
			141
		],
		[
			251,
			260
		],
		[
			251,
			298
		],
		[
			143,
			144
		],
		[
			58,
			74
		],
		[
			58,
			75
		],
		[
			74,
			75
		],
		[
			273,
			306
		],
		[
			276,
			306
		],
		[
			126,
			273
		],
		[
			192,
			193
		],
		[
			41,
			307
		],
		[
			141,
			316
		],
		[
			141,
			315
		],
		[
			74,
			288
		],
		[
			219,
			220
		],
		[
			188,
			189
		],
		[
			180,
			294
		],
		[
			68,
			71
		],
		[
			67,
			68
		],
		[
			224,
			267
		],
		[
			44,
			323
		],
		[
			44,
			45
		],
		[
			179,
			180
		],
		[
			27,
			291
		],
		[
			26,
			27
		],
		[
			205,
			283
		],
		[
			222,
			223
		],
		[
			75,
			328
		],
		[
			76,
			328
		],
		[
			75,
			76
		],
		[
			257,
			264
		],
		[
			257,
			280
		],
		[
			264,
			280
		],
		[
			223,
			224
		],
		[
			144,
			145
		],
		[
			71,
			303
		],
		[
			130,
			131
		],
		[
			199,
			264
		],
		[
			199,
			257
		],
		[
			248,
			249
		],
		[
			107,
			315
		],
		[
			200,
			264
		],
		[
			202,
			264
		],
		[
			16,
			290
		],
		[
			16,
			17
		],
		[
			212,
			238
		],
		[
			212,
			239
		],
		[
			238,
			239
		],
		[
			157,
			159
		],
		[
			96,
			151
		],
		[
			95,
			96
		],
		[
			162,
			252
		],
		[
			161,
			162
		],
		[
			79,
			272
		],
		[
			237,
			238
		],
		[
			46,
			47
		],
		[
			46,
			322
		],
		[
			153,
			154
		],
		[
			153,
			266
		],
		[
			154,
			266
		],
		[
			63,
			72
		],
		[
			72,
			73
		],
		[
			155,
			266
		],
		[
			168,
			169
		],
		[
			169,
			170
		],
		[
			73,
			74
		],
		[
			56,
			76
		],
		[
			60,
			61
		],
		[
			48,
			162
		],
		[
			162,
			163
		],
		[
			12,
			37
		],
		[
			86,
			310
		],
		[
			48,
			76
		],
		[
			48,
			272
		],
		[
			64,
			309
		],
		[
			72,
			309
		],
		[
			48,
			49
		],
		[
			11,
			12
		],
		[
			165,
			166
		],
		[
			166,
			167
		],
		[
			151,
			286
		],
		[
			150,
			151
		],
		[
			63,
			309
		],
		[
			126,
			127
		],
		[
			158,
			159
		],
		[
			157,
			158
		],
		[
			168,
			256
		],
		[
			167,
			168
		],
		[
			17,
			18
		],
		[
			20,
			21
		],
		[
			209,
			325
		],
		[
			208,
			209
		],
		[
			205,
			206
		],
		[
			7,
			8
		],
		[
			8,
			9
		],
		[
			257,
			261
		],
		[
			261,
			280
		],
		[
			212,
			311
		],
		[
			46,
			180
		],
		[
			46,
			183
		],
		[
			85,
			86
		],
		[
			82,
			83
		],
		[
			209,
			210
		],
		[
			199,
			200
		],
		[
			197,
			198
		],
		[
			198,
			199
		],
		[
			323,
			324
		],
		[
			103,
			104
		],
		[
			9,
			10
		],
		[
			99,
			100
		],
		[
			99,
			275
		],
		[
			88,
			250
		],
		[
			216,
			304
		],
		[
			215,
			216
		],
		[
			215,
			304
		],
		[
			214,
			304
		],
		[
			101,
			102
		],
		[
			213,
			214
		]
	],
	"score": 0.012515777524966219
}